strictyaml/__init__.py
strictyaml/any_validator.py
strictyaml/compound.py
strictyaml/constants.py
strictyaml/dumper.py
strictyaml/exceptions.py
strictyaml/parser.py
strictyaml/representation.py
strictyaml/scalar.py
strictyaml/utils.py
strictyaml/validators.py
strictyaml/yamllocation.py
strictyaml/yamlpointer.py
strictyaml/ruamel/__init__.py
strictyaml/ruamel/anchor.py
strictyaml/ruamel/comments.py
strictyaml/ruamel/compat.py
strictyaml/ruamel/composer.py
strictyaml/ruamel/configobjwalker.py
strictyaml/ruamel/constructor.py
strictyaml/ruamel/cyaml.py
strictyaml/ruamel/dumper.py
strictyaml/ruamel/emitter.py
strictyaml/ruamel/error.py
strictyaml/ruamel/events.py
strictyaml/ruamel/loader.py
strictyaml/ruamel/main.py
strictyaml/ruamel/nodes.py
strictyaml/ruamel/parser.py
strictyaml/ruamel/reader.py
strictyaml/ruamel/representer.py
strictyaml/ruamel/resolver.py
strictyaml/ruamel/scalarbool.py
strictyaml/ruamel/scalarfloat.py
strictyaml/ruamel/scalarint.py
strictyaml/ruamel/scalarstring.py
strictyaml/ruamel/scanner.py
strictyaml/ruamel/serializer.py
strictyaml/ruamel/timestamp.py
strictyaml/ruamel/tokens.py
strictyaml/ruamel/util.py
strictyaml-1.7.3.dist-info/LICENSE.txt
strictyaml-1.7.3.dist-info/METADATA
strictyaml-1.7.3.dist-info/WHEEL
strictyaml-1.7.3.dist-info/top_level.txt
strictyaml-1.7.3.dist-info/RECORD
