Metadata-Version: 2.1
Name: strictyaml
Version: 1.7.3
Summary: Strict, typed YAML parser
Author-email: Colm O'Connor <colm.oconnor.github@gmail.com>
License: MIT
Project-URL: homepage, https://hitchdev.com/strictyaml
Project-URL: documentation, https://hitchdev.com/strictyaml/using
Project-URL: repository, https://github.com/crdoconnor/strictyaml
Project-URL: changelog, https://hitchdev.com/strictyaml/changelog
Keywords: yaml
Classifier: Programming Language :: Python :: 3
Classifier: License :: OSI Approved :: MIT License
Classifier: Topic :: Text Processing :: Markup
Classifier: Topic :: Software Development :: Libraries
Classifier: Natural Language :: English
Requires-Python: >=3.7.0
License-File: LICENSE.txt
